<configs>	
	<set xpath="/entity_classes/entity_class/property[@name='LootDropProb']/@value">0.1</set>
	
	<remove xpath="/entity_classes/entity_class[@name='zombieTemplateMale']/property[@name='LootDropEntityClass']"/>
	<append xpath="/entity_classes/entity_class[@name='zombieTemplateMale']">
		<property name="LootDropEntityClass" value="EntityLootContainer_zombie"/>
	</append>
	<remove xpath="/entity_classes/entity_class[@name='zombieWightFeral']/property[@name='LootDropEntityClass']"/>
	<append xpath="/entity_classes/entity_class[@name='zombieWightFeral']">
		<property name="LootDropEntityClass" value="EntityLootContainer_Feral"/>
	</append>
	<append xpath="/entity_classes/entity_class[@name='zombieBoeFeral']">
		<property name="LootDropEntityClass" value="EntityLootContainer_Feral"/>
	</append>
	<append xpath="/entity_classes/entity_class[@name='zombieFootballPlayer']">
		<property name="LootDropEntityClass" value="EntityLootContainer_zombieFootballPlayer"/>
	</append>
	<remove xpath="/entity_classes/entity_class[@name='zombieFemaleFatFeral']/property[@name='LootDropEntityClass']"/>
	<append xpath="/entity_classes/entity_class[@name='zombieFemaleFatFeral']">
		<property name="LootDropEntityClass" value="EntityLootContainer_Feral"/>
	</append>
	<append xpath="/entity_classes/entity_class[@name='zombieJoeFeral']">
		<property name="LootDropEntityClass" value="EntityLootContainer_Feral"/>
	</append>
	<remove xpath="/entity_classes/entity_class[@name='zombieMoeFeral']/property[@name='LootDropEntityClass']"/>
	<append xpath="/entity_classes/entity_class[@name='zombieMoeFeral']">
		<property name="LootDropEntityClass" value="EntityLootContainer_Feral"/>
	</append>
	<append xpath="/entity_classes/entity_class[@name='zombieArleneFeral']">
		<property name="LootDropEntityClass" value="EntityLootContainer_Feral"/>
	</append>
	<append xpath="/entity_classes/entity_class[@name='zombieLab']">
		<property name="LootDropEntityClass" value="EntityLootContainer_zombieLab"/>
	</append>
	<append xpath="/entity_classes/entity_class[@name='zombieLabFeral']">
		<property name="LootDropEntityClass" value="EntityLootContainer_Feral"/>
	</append>
	<append xpath="/entity_classes/entity_class[@name='zombieLabRadiated']">
		<property name="LootDropEntityClass" value="EntityLootContainer_Feral"/>
	</append>
	<append xpath="/entity_classes/entity_class[@name='legendaryZombieLab']">
		<property name="LootDropEntityClass" value="EntityLootContainer_Legendary"/>
	</append>
	<append xpath="/entity_classes/entity_class[@name='zombieDarleneFeral']">
		<property name="LootDropEntityClass" value="EntityLootContainer_Feral"/>
	</append>
	<append xpath="/entity_classes/entity_class[@name='zombieMarleneFeral']">
		<property name="LootDropEntityClass" value="EntityLootContainer_Feral"/>
	</append>
	<append xpath="/entity_classes/entity_class[@name='zombieMarleneRadiated']">
		<property name="LootDropEntityClass" value="EntityLootContainer_Feral"/>
	</append>
	<append xpath="/entity_classes/entity_class[@name='zombieYoFeral']">
		<property name="LootDropEntityClass" value="EntityLootContainer_Feral"/>
	</append>
	<append xpath="/entity_classes/entity_class[@name='zombieSteveFeral']">
		<property name="LootDropEntityClass" value="EntityLootContainer_Feral"/>
	</append>
	<remove xpath="/entity_classes/entity_class[@name='zombieSteveRadiated']/property[@name='LootDropEntityClass']"/>
	<append xpath="/entity_classes/entity_class[@name='zombieSteveRadiated']">
		<property name="LootDropEntityClass" value="EntityLootContainer_Feral"/>
	</append>
	<append xpath="/entity_classes/entity_class[@name='zombieSteveCrawlerFeral']">
		<property name="LootDropEntityClass" value="EntityLootContainer_Feral"/>
	</append>
	<append xpath="/entity_classes/entity_class[@name='zombieBusinessMan']">
		<property name="LootDropEntityClass" value="EntityLootContainer_zombieBusinessMan"/>
	</append>
	<append xpath="/entity_classes/entity_class[@name='zombieBusinessManFeral']">
		<property name="LootDropEntityClass" value="EntityLootContainer_Feral"/>
	</append>
	<append xpath="/entity_classes/entity_class[@name='legendaryZombieBusinessMan']">
		<property name="LootDropEntityClass" value="EntityLootContainer_Legendary"/>
	</append>
	<append xpath="/entity_classes/entity_class[@name='zombieSnow']">
		<property name="LootDropEntityClass" value="EntityLootContainer_zombieSnow"/>
	</append>
	<remove xpath="/entity_classes/entity_class[@name='zombieSnowFeral']/property[@name='LootDropEntityClass']"/>
	<append xpath="/entity_classes/entity_class[@name='zombieSnowFeral']">
		<property name="LootDropEntityClass" value="EntityLootContainer_Feral"/>
	</append>
	<append xpath="/entity_classes/entity_class[@name='zombieSpiderFeral']">
		<property name="LootDropEntityClass" value="EntityLootContainer_Feral"/>
	</append>
	<append xpath="/entity_classes/entity_class[@name='zombieBurnt']">
		<property name="LootDropEntityClass" value="EntityLootContainer_zombieBurnt"/>
	</append>
	<append xpath="/entity_classes/entity_class[@name='zombieNurse']">
		<property name="LootDropEntityClass" value="EntityLootContainer_zombieNurse"/>
	</append>
	<append xpath="/entity_classes/entity_class[@name='zombieNurseFeral']">
		<property name="LootDropEntityClass" value="EntityLootContainer_Feral"/>
	</append>
	<remove xpath="/entity_classes/entity_class[@name='zombieFatHawaiian']/property[@name='LootDropEntityClass']"/>
	<append xpath="/entity_classes/entity_class[@name='zombieFatHawaiian']">
		<property name="LootDropEntityClass" value="EntityLootContainer_zombieFatHawaiian"/>
	</append>
	<remove xpath="/entity_classes/entity_class[@name='zombieFatHawaiianFeral']/property[@name='LootDropEntityClass']"/>
	<append xpath="/entity_classes/entity_class[@name='zombieFatHawaiianFeral']">
		<property name="LootDropEntityClass" value="EntityLootContainer_Feral"/>
	</append>
	<remove xpath="/entity_classes/entity_class[@name='zombieFatCop']/property[@name='LootDropEntityClass']"/>
	<append xpath="/entity_classes/entity_class[@name='zombieFatCop']">
		<property name="LootDropEntityClass" value="EntityLootContainer_zombieFatCop"/>
	</append>
	<append xpath="/entity_classes/entity_class[@name='zombieFatCopFeral']">
		<property name="LootDropEntityClass" value="EntityLootContainer_Feral"/>
	</append>
	<append xpath="/entity_classes/entity_class[@name='zombieMaleHazmat']">
		<property name="LootDropEntityClass" value="EntityLootContainer_zombieMaleHazmat"/>
	</append>
	<append xpath="/entity_classes/entity_class[@name='zombieUtilityWorker']">
		<property name="LootDropEntityClass" value="EntityLootContainer_zombieUtilityWorker"/>
	</append>
	<append xpath="/entity_classes/entity_class[@name='zombieUtilityWorkerFeral']">
		<property name="LootDropEntityClass" value="EntityLootContainer_Feral"/>
	</append>
	<append xpath="/entity_classes/entity_class[@name='legendaryZombieUtilityWorker']">
		<property name="LootDropEntityClass" value="EntityLootContainer_Legendary"/>
	</append>
	<append xpath="/entity_classes/entity_class[@name='zombieSoldier']">
		<property name="LootDropEntityClass" value="EntityLootContainer_zombieSoldier"/>
	</append>
	<append xpath="/entity_classes/entity_class[@name='zombieSoldierFeral']">
		<property name="LootDropEntityClass" value="EntityLootContainer_Feral"/>
	</append>
	<append xpath="/entity_classes/entity_class[@name='zombieSkateboarderFeral']">
		<property name="LootDropEntityClass" value="EntityLootContainer_Feral"/>
	</append>
	<append xpath="/entity_classes/entity_class[@name='zombieCheerleaderFeral']">
		<property name="LootDropEntityClass" value="EntityLootContainer_Feral"/>
	</append>
	<append xpath="/entity_classes/entity_class[@name='zombieOldTimerFeral']">
		<property name="LootDropEntityClass" value="EntityLootContainer_Feral"/>
	</append>
	<remove xpath="/entity_classes/entity_class[@name='zombieBiker']/property[@name='LootDropEntityClass']"/>
	<append xpath="/entity_classes/entity_class[@name='zombieBiker']">
		<property name="LootDropEntityClass" value="EntityLootContainer_zombieBiker"/>
	</append>
	<remove xpath="/entity_classes/entity_class[@name='zombieBikerFeral']/property[@name='LootDropEntityClass']"/>
	<append xpath="/entity_classes/entity_class[@name='zombieBikerFeral']">
		<property name="LootDropEntityClass" value="EntityLootContainer_Feral"/>
	</append>
	<append xpath="/entity_classes/entity_class[@name='zombieFarmer']">
		<property name="LootDropEntityClass" value="EntityLootContainer_zombieFarmer"/>
	</append>
	<append xpath="/entity_classes/entity_class[@name='zombieFarmerFeral']">
		<property name="LootDropEntityClass" value="EntityLootContainer_Feral"/>
	</append>
	<append xpath="/entity_classes/entity_class[@name='zombieStripperFeral']">
		<property name="LootDropEntityClass" value="EntityLootContainer_Feral"/>
	</append>
	
	<append xpath="/entity_classes">
		<entity_class name="EntityLootContainer_zombie">
			<property name="Mesh" value="LootContainers/zpackPrefab"/>
			<property name="ModelType" value="Custom"/>
			<property name="Prefab" value="Backpack"/>
			<property name="Class" value="EntityLootContainer"/>
			<property name="Parent" value="Backpack"/>
			<property name="IsEnemyEntity" value="false"/>
			<property name="TimeStayAfterDeath" value="600"/>
			<property name="LootListOnDeath" value="200"/>
			<property name="Faction" value="none"/>
		</entity_class>
		<entity_class name="EntityLootContainer_Feral" extends="EntityLootContainer_zombie">
			<property name="LootListOnDeath" value="201"/>
		</entity_class>
		<entity_class name="EntityLootContainer_Legendary" extends="EntityLootContainer_zombie">
			<property name="LootListOnDeath" value="202"/>
		</entity_class>
		<entity_class name="EntityLootContainer_zombieFootballPlayer" extends="EntityLootContainer_zombie">
			<property name="LootListOnDeath" value="203"/>
		</entity_class>
		<entity_class name="EntityLootContainer_zombieLab" extends="EntityLootContainer_zombie">
			<property name="LootListOnDeath" value="204"/>
		</entity_class>
		<entity_class name="EntityLootContainer_zombieBusinessMan" extends="EntityLootContainer_zombie">
			<property name="LootListOnDeath" value="205"/>
		</entity_class>
		<entity_class name="EntityLootContainer_zombieSnow" extends="EntityLootContainer_zombie">
			<property name="LootListOnDeath" value="206"/>
		</entity_class>
		<entity_class name="EntityLootContainer_zombieBurnt" extends="EntityLootContainer_zombie">
			<property name="LootListOnDeath" value="207"/>
		</entity_class>
		<entity_class name="EntityLootContainer_zombieNurse" extends="EntityLootContainer_zombie">
			<property name="LootListOnDeath" value="208"/>
		</entity_class>
		<entity_class name="EntityLootContainer_zombieFatHawaiian" extends="EntityLootContainer_zombie">
			<property name="LootListOnDeath" value="209"/>
		</entity_class>
		<entity_class name="EntityLootContainer_zombieFatCop" extends="EntityLootContainer_zombie">
			<property name="LootListOnDeath" value="210"/>
		</entity_class>
		<entity_class name="EntityLootContainer_zombieMaleHazmat" extends="EntityLootContainer_zombie">
			<property name="LootListOnDeath" value="211"/>
		</entity_class>
		<entity_class name="EntityLootContainer_zombieUtilityWorker" extends="EntityLootContainer_zombie">
			<property name="LootListOnDeath" value="212"/>
		</entity_class>
		<entity_class name="EntityLootContainer_zombieSoldier" extends="EntityLootContainer_zombie">
			<property name="LootListOnDeath" value="213"/>
		</entity_class>
		<entity_class name="EntityLootContainer_zombieBiker" extends="EntityLootContainer_zombie">
			<property name="LootListOnDeath" value="214"/>
		</entity_class>
		<entity_class name="EntityLootContainer_zombieFarmer" extends="EntityLootContainer_zombie">
			<property name="LootListOnDeath" value="215"/>
		</entity_class>
	</append>
</configs>